data_structures/__init__.py
data_structures/elements.py
data_structures/queues.py
data_structures/stacks.py
tests/__init__.py
tests/test_elements.py
tests/test_queues.py
tests/test_stacks.py
data_structures_nicorodc-0.3.1.dist-info/LICENSE
data_structures_nicorodc-0.3.1.dist-info/METADATA
data_structures_nicorodc-0.3.1.dist-info/WHEEL
data_structures_nicorodc-0.3.1.dist-info/top_level.txt
data_structures_nicorodc-0.3.1.dist-info/RECORD
