Metadata-Version: 2.1
Name: data-structures-nicorodc
Version: 0.3.1
Summary: Useful data structures for problem solving
Home-page: https://github.com/taurusongithub/data_structures
Author: Nicolás Agustín Rodriguez Castro
Author-email: nicorodc@gmail.com
License: UNKNOWN
Project-URL: Bug Tracker, https://github.com/taurusongithub/data_structures/issues
Platform: UNKNOWN
Classifier: Programming Language :: Python :: 3
Classifier: License :: OSI Approved :: MIT License
Classifier: Operating System :: OS Independent
Requires-Python: >=3
License-File: LICENSE
